django_comments_xtd/__init__.py
django_comments_xtd/admin.py
django_comments_xtd/apps.py
django_comments_xtd/forms.py
django_comments_xtd/models.py
django_comments_xtd/moderation.py
django_comments_xtd/signals.py
django_comments_xtd/signed.py
django_comments_xtd/urls.py
django_comments_xtd/utils.py
django_comments_xtd/views.py
django_comments_xtd/api/__init__.py
django_comments_xtd/api/frontend.py
django_comments_xtd/api/serializers.py
django_comments_xtd/api/urls.py
django_comments_xtd/api/views.py
django_comments_xtd/conf/__init__.py
django_comments_xtd/conf/defaults.py
django_comments_xtd/locale/de/LC_MESSAGES/django.po
django_comments_xtd/locale/de/LC_MESSAGES/djangojs.po
django_comments_xtd/locale/es/LC_MESSAGES/django.po
django_comments_xtd/locale/es/LC_MESSAGES/djangojs.po
django_comments_xtd/locale/fi/LC_MESSAGES/django.po
django_comments_xtd/locale/fi/LC_MESSAGES/djangojs.po
django_comments_xtd/locale/fr/LC_MESSAGES/django.po
django_comments_xtd/locale/fr/LC_MESSAGES/djangojs.po
django_comments_xtd/locale/it/LC_MESSAGES/django.po
django_comments_xtd/locale/it/LC_MESSAGES/djangojs.po
django_comments_xtd/locale/nl/LC_MESSAGES/django.po
django_comments_xtd/locale/nl/LC_MESSAGES/djangojs.po
django_comments_xtd/locale/no/LC_MESSAGES/django.po
django_comments_xtd/locale/no/LC_MESSAGES/djangojs.po
django_comments_xtd/locale/ru/LC_MESSAGES/django.po
django_comments_xtd/locale/ru/LC_MESSAGES/djangojs.po
django_comments_xtd/locale/zh_Hans/LC_MESSAGES/django.po
django_comments_xtd/locale/zh_Hans/LC_MESSAGES/djangojs.po
django_comments_xtd/management/__init__.py
django_comments_xtd/management/commands/__init__.py
django_comments_xtd/management/commands/initialize_nested_count.py
django_comments_xtd/management/commands/populate_xtdcomments.py
django_comments_xtd/migrations/0001_initial.py
django_comments_xtd/migrations/0002_blacklisteddomain.py
django_comments_xtd/migrations/0003_auto_20170220_1333.py
django_comments_xtd/migrations/0004_auto_20170221_1510.py
django_comments_xtd-2.10.10.dist-info/licenses/AUTHORS
django_comments_xtd-2.10.10.dist-info/licenses/LICENSE
django_comments_xtd-2.10.10.dist-info/METADATA
django_comments_xtd-2.10.10.dist-info/WHEEL
django_comments_xtd-2.10.10.dist-info/top_level.txt
django_comments_xtd-2.10.10.dist-info/RECORD
