Metadata-Version: 2.4
Name: django-comments-xtd
Version: 2.10.10
Summary: Commenting Django app with threads, follow up notifications and email confirmation.
Author-email: Daniela Rus Morales <danirus@eml.cc>
License-Expression: BSD-2-Clause
Project-URL: Homepage, https://github.com/danirus/django-comments-xtd
Project-URL: Documentation, https://django-comments.xtd.readthedocs.io
Classifier: Development Status :: 5 - Production/Stable
Classifier: Environment :: Web Environment
Classifier: Intended Audience :: Developers
Classifier: Operating System :: OS Independent
Classifier: Programming Language :: Python
Classifier: Programming Language :: Python :: 3
Classifier: Framework :: Django
Classifier: Natural Language :: English
Classifier: Topic :: Internet :: WWW/HTTP :: Dynamic Content :: News/Diary
Requires-Python: >=3.10
License-File: LICENSE
License-File: AUTHORS
Requires-Dist: Django<6,>=4
Requires-Dist: django-contrib-comments<2.3,>=2.2
Requires-Dist: djangorestframework<3.17,>=3.12
Requires-Dist: docutils
Requires-Dist: pytz
Requires-Dist: six
Provides-Extra: dev
Requires-Dist: coverage<7.7,>=7.6; extra == "dev"
Requires-Dist: django-coverage-plugin<3.2,>=3.1; extra == "dev"
Requires-Dist: pre-commit>=4.0.1; extra == "dev"
Requires-Dist: pytest<8.4,>=8.3; extra == "dev"
Requires-Dist: pytest-cov<6.1,>=6.0; extra == "dev"
Requires-Dist: pytest-django<4.10,>=4.9; extra == "dev"
Requires-Dist: ruff<1,>=0.11.0; extra == "dev"
Requires-Dist: tox<4.26,>=4.25; extra == "dev"
Provides-Extra: docs
Requires-Dist: sphinx<9,>=8; extra == "docs"
Requires-Dist: myst-parser<4.1,>=4.0.0; extra == "docs"
Requires-Dist: sphinx-colorschemed-images>=0.2.2; extra == "docs"
Requires-Dist: sphinx-copybutton<1.0.0,>=0.5.2; extra == "docs"
Requires-Dist: sphinx-nefertiti>=0.8.5; extra == "docs"
Dynamic: license-file
